nnmeta/__init__.py
nnmeta/nnmeta.py
nnmeta/tests/__init__.py
nnmeta-2.0.1.dist-info/LICENSE.txt
nnmeta-2.0.1.dist-info/METADATA
nnmeta-2.0.1.dist-info/WHEEL
nnmeta-2.0.1.dist-info/top_level.txt
nnmeta-2.0.1.dist-info/RECORD
