Metadata-Version: 2.1
Name: nnmeta
Version: 2.0.1
Summary: NNmeta based on Netpack
Home-page: https://github.com/AlexanderDKazakov/nnmeta
Author: Alexander D. Kazakov
Author-email: alexander.d.kazakov@gmail.com
License: MIT
Keywords: neural network
Platform: UNKNOWN
Classifier: Development Status :: 4 - Beta
Classifier: Intended Audience :: Developers
Classifier: Topic :: Software Development :: Build Tools
Classifier: License :: OSI Approved :: MIT License
Classifier: Programming Language :: Python :: 3.7
Classifier: Programming Language :: Python :: 3.8
Classifier: Programming Language :: Python :: 3.9
Requires-Python: >=3.7
Requires-Dist: nnpackage
Requires-Dist: storer
